gradnorm_pytorch/__init__.py
gradnorm_pytorch/gradnorm_pytorch.py
gradnorm_pytorch/mocks.py
gradnorm_pytorch-0.2.1.dist-info/licenses/LICENSE
gradnorm_pytorch-0.2.1.dist-info/METADATA
gradnorm_pytorch-0.2.1.dist-info/WHEEL
gradnorm_pytorch-0.2.1.dist-info/top_level.txt
gradnorm_pytorch-0.2.1.dist-info/RECORD
